alu.v
`timescale 1ps/1ps
module alu(
    input [15:0] A,  // input 1
    input [15:0] B,  // input 2
    input [2:0] fun, // Selector
    // Flags
    output N, // Negative
    output Z, // Zero
    output C, // Carry
    output V, // Overflow
    output reg [15:0] R
);
    // Intermediate Results
    wire [16:0] R_add, R_sub;
    wire [15:0] R_AND, R_OR, R_NOR, R_LSL, R_LSR, R_ASR;
    wire [16:0] A_ext = {1'b0, A};
    wire [16:0] B_ext = {1'b0, B};
    
    // ALU Intermediate Results
    assign R_add = A_ext + B_ext;
    assign R_sub = A_ext - B_ext;
    assign R_AND = A & B;
    assign R_OR  = A | B;
    assign R_NOR = ~(A | B);
    assign R_LSL = A << B[3:0];
    assign R_LSR = A >> B[3:0];
    assign R_ASR = $signed(A) >>> B[3:0];
    
    // MUX / ALU result selection
    always @(*) begin
        R = 16'd0;
        case(fun)
            3'b000: R = R_add[15:0]; // ADD
            3'b001: R = R_sub[15:0]; // SUB
            3'b010: R = R_AND; // AND
            3'b011: R = R_OR;  // OR
            3'b100: R = R_NOR; // NOR
            3'b101: R = R_LSL; // LSL
            3'b110: R = R_LSR; // LSR
            3'b111: R = R_ASR; // ASR
            default: ;
        endcase
    end

    // Flags
    assign N = R[15]; // Negative
    assign Z = (R == 16'b0); // Zero
    
    // Carry flag for ADD and SUB
    wire C_add = (fun == 3'b000) ? R_add[16] : 1'b0;
    wire C_sub = (fun == 3'b001) ? ~R_sub[16] : 1'b0;
    assign C = C_add | C_sub;

    // Overflow flag for ADD and SUB
    wire V_add, V_sub;
    assign V_add = (fun == 3'b000) ? ((A[15] == B[15]) && (R_add[15] != A[15])) : 1'b0;
    assign V_sub = (fun == 3'b001) ? ((A[15] != B[15]) && (R_sub[15] != A[15])) : 1'b0;
    assign V = V_add | V_sub;

endmodule

alu_tb.v
`timescale 1ps/1ps
module alu_tb;
    reg  [15:0] A, B;
    reg  [2:0]  fun;
    wire N, Z, C, V;
    wire [15:0] R;

    alu dut (.A(A), .B(B), .fun(fun), .N(N), .Z(Z), .C(C), .V(V), .R(R));

    task do_test;
        input [15:0] a, b;
        input [2:0]  op;
        reg   [16:0] expR_ext;
        reg   [15:0] expR;
        reg   expN, expZ, expC, expV;
    begin
        A = a; B = b; fun = op;
        #1;

        // Expected result (17-bit for carry/borrow)
        case (op)
            3'b000: expR_ext = {1'b0, a} + {1'b0, b};
            3'b001: expR_ext = {1'b0, a} - {1'b0, b};
            3'b010: expR_ext = {1'b0, (a & b)};
            3'b011: expR_ext = {1'b0, (a | b)};
            3'b100: expR_ext = {1'b0, ~(a | b)};
            3'b101: expR_ext = {1'b0, (a << b[3:0])};
            3'b110: expR_ext = {1'b0, (a >> b[3:0])};
            3'b111: expR_ext = {1'b0, ($signed(a) >>> b[3:0])};
            default: expR_ext = 17'd0;
        endcase
        expR = expR_ext[15:0];

        // Flags (C_sub = ~borrow to match your ALU)
        expN = expR[15];
        expZ = (expR == 16'd0);
        expC = (op == 3'b000) ? expR_ext[16] :
               (op == 3'b001) ? ~expR_ext[16] : 1'b0;
        expV = (op == 3'b000) ? ((a[15] == b[15]) && (expR[15] != a[15])) :
               (op == 3'b001) ? ((a[15] != b[15]) && (expR[15] != a[15])) : 1'b0;

        if (R !== expR || N !== expN || Z !== expZ || C !== expC || V !== expV) begin
            $display("FAIL op=%b A=%h B=%h expR=%h gotR=%h expN=%b gotN=%b expZ=%b gotZ=%b expC=%b gotC=%b expV=%b gotV=%b",
                     op, a, b, expR, R, expN, N, expZ, Z, expC, C, expV, V);
            $stop;
        end else begin
            $display("PASS op=%b A=%h B=%h -> R=%h N=%b Z=%b C=%b V=%b", op, a, b, R, N, Z, C, V);
        end
    end
    endtask

    initial begin
        do_test(16'h0001, 16'h0001, 3'b000);
        do_test(16'hFFFF, 16'h0001, 3'b000);
        do_test(16'h7FFF, 16'h0001, 3'b000);
        do_test(16'h0003, 16'h0007, 3'b001);
        do_test(16'h0000, 16'h0001, 3'b001);
        do_test(16'h8000, 16'h7FFF, 3'b001);
        do_test(16'h00FF, 16'h0F0F, 3'b010);
        do_test(16'h00FF, 16'h0F0F, 3'b011);
        do_test(16'h00FF, 16'h0F0F, 3'b100);
        do_test(16'h0001, 16'h0004, 3'b101);
        do_test(16'h8000, 16'h0001, 3'b110);
        do_test(16'h8000, 16'h0001, 3'b111);

        $display("All tests completed.");
        $finish;
    end
endmodule

alu_tb.vcd
$date
	Sat Dec 20 16:11:30 2025
$end
$version
	Icarus Verilog
$end
$timescale
	1ps
$end
$scope module alu_tb $end
$var wire 1 ! C $end
$var wire 1 " N $end
$var wire 16 # R [15:0] $end
$var wire 1 $ V $end
$var wire 1 % Z $end
$var reg 16 & A [15:0] $end
$var reg 16 ' B [15:0] $end
$var reg 3 ( fun [2:0] $end
$scope module dut $end
$var wire 16 ) A [15:0] $end
$var wire 17 * A_ext [16:0] $end
$var wire 16 + B [15:0] $end
$var wire 17 , B_ext [16:0] $end
$var wire 1 ! C $end
$var wire 1 - C_add $end
$var wire 1 . C_sub $end
$var wire 1 " N $end
$var wire 16 / R_AND [15:0] $end
$var wire 16 0 R_ASR [15:0] $end
$var wire 16 1 R_LSL [15:0] $end
$var wire 16 2 R_LSR [15:0] $end
$var wire 16 3 R_NOR [15:0] $end
$var wire 16 4 R_OR [15:0] $end
$var wire 17 5 R_add [16:0] $end
$var wire 17 6 R_sub [16:0] $end
$var wire 1 $ V $end
$var wire 1 7 V_add $end
$var wire 1 8 V_sub $end
$var wire 1 % Z $end
$var wire 3 9 fun [2:0] $end
$var reg 16 : R [15:0] $end
$upscope $end
$scope task do_test $end
$var reg 16 ; a [15:0] $end
$var reg 16 < b [15:0] $end
$var reg 1 = expC $end
$var reg 1 > expN $end
$var reg 16 ? expR [15:0] $end
$var reg 17 @ expR_ext [16:0] $end
$var reg 1 A expV $end
$var reg 1 B expZ $end
$var reg 3 C op [2:0] $end
$upscope $end
$upscope $end
$enddefinitions $end
#0
$dumpvars
b0 C
xB
xA
bx @
bx ?
x>
x=
b1 <
b1 ;
b10 :
b0 9
08
07
b0 6
b10 5
b1 4
b1111111111111110 3
b0 2
b10 1
b0 0
b1 /
0.
0-
b1 ,
b1 +
b1 *
b1 )
b0 (
b1 '
b1 &
0%
0$
b10 #
0"
0!
$end
#1
1!
b0 3
1-
b1111111111111111 4
b0 :
1%
b0 #
b1111111111111111 &
b1111111111111111 )
b10000000000000000 5
b1111111111111110 6
b1111111111111111 *
b1111111111111110 1
b111111111111111 2
b1111111111111111 0
b1111111111111111 ;
0A
0=
0B
0>
b10 ?
b10 @
#2
1$
17
0!
b1000000000000000 3
0-
1"
b111111111111111 4
b1000000000000000 :
0%
b1000000000000000 #
b111111111111111 &
b111111111111111 )
b1000000000000000 5
b111111111111110 6
b111111111111111 *
b11111111111111 2
b11111111111111 0
b111111111111111 ;
1=
1B
b0 ?
b10000000000000000 @
#3
0!
0$
b1111111111111000 3
0.
07
b11 /
b111 4
b1111111111111100 :
0%
b1111111111111100 #
b1 (
b1 9
b111 '
b111 +
b111 ,
b11 &
b11 )
b1010 5
b11111111111111100 6
b11 *
b110000000 1
b0 2
b0 0
b1 C
b111 <
b11 ;
1A
0=
0B
1>
b1000000000000000 ?
b1000000000000000 @
#4
b1111111111111110 3
b0 /
b1 4
b1111111111111111 :
0%
b1111111111111111 #
b1 '
b1 +
b1 ,
b0 &
b0 )
b1 5
b11111111111111111 6
b0 *
b0 1
b1 <
b0 ;
0A
b1111111111111100 ?
b11111111111111100 @
#5
1$
1!
18
1.
b0 3
0"
b1111111111111111 4
b1 :
0%
b1 #
b111111111111111 '
b111111111111111 +
b111111111111111 ,
b1000000000000000 &
b1000000000000000 )
b1111111111111111 5
b1 6
b1000000000000000 *
b1 2
b1111111111111111 0
b111111111111111 <
b1000000000000000 ;
b1111111111111111 ?
b11111111111111111 @
#6
0!
0$
b1111000000000000 3
0.
08
b1111 /
b111111111111 4
b1111 :
0%
b1111 #
b10 (
b10 9
b111100001111 '
b111100001111 +
b111100001111 ,
b11111111 &
b11111111 )
b1000000001110 5
b11111000111110000 6
b11111111 *
b1000000000000000 1
b0 2
b0 0
b10 C
b111100001111 <
b11111111 ;
1A
1=
0>
b1 ?
b1 @
#7
b111111111111 :
0%
b111111111111 #
b11 (
b11 9
b11 C
0A
0=
b1111 ?
b1111 @
#8
1"
b1111000000000000 :
0%
b1111000000000000 #
b100 (
b100 9
b100 C
b111111111111 ?
b111111111111 @
#9
0"
b1111111111111010 3
b10000 1
b0 /
b101 4
b10000 :
0%
b10000 #
b101 (
b101 9
b100 '
b100 +
b100 ,
b1 &
b1 )
b101 5
b11111111111111101 6
b1 *
b101 C
b100 <
b1 ;
1>
b1111000000000000 ?
b1111000000000000 @
#10
b111111111111110 3
b1000000000000001 4
b100000000000000 :
0%
b100000000000000 #
b110 (
b110 9
b1 '
b1 +
b1 ,
b1000000000000000 &
b1000000000000000 )
b1000000000000001 5
b111111111111111 6
b1000000000000000 *
b0 1
b100000000000000 2
b1100000000000000 0
b110 C
b1 <
b1000000000000000 ;
0>
b10000 ?
b10000 @
#11
1"
b1100000000000000 :
0%
b1100000000000000 #
b111 (
b111 9
b111 C
b100000000000000 ?
b100000000000000 @
#12
1>
b1100000000000000 ?
b1100000000000000 @
